ida_domain_mcp/__init__.py
ida_domain_mcp/ida_tools.py
ida_domain_mcp/main.py
ida_domain_mcp-0.1.2.dist-info/licenses/LICENSE
ida_domain_mcp-0.1.2.dist-info/METADATA
ida_domain_mcp-0.1.2.dist-info/WHEEL
ida_domain_mcp-0.1.2.dist-info/entry_points.txt
ida_domain_mcp-0.1.2.dist-info/top_level.txt
ida_domain_mcp-0.1.2.dist-info/RECORD
