Metadata-Version: 2.4
Name: ida-domain-mcp
Version: 0.1.2
Summary: MCP plugin for IDA Pro/IDA Free that uses ida-domain for database access
Author-email: Mimi <stevenjoezhang@gmail.com>, xxyyue <xxyyyue@gmail.com>
License-Expression: MIT
Project-URL: Repository, https://github.com/xxyyue/ida_domain_mcp
Project-URL: Issues, https://github.com/xxyyue/ida_domain_mcp/issues
Requires-Python: >=3.11
License-File: LICENSE
Requires-Dist: fastmcp>=2.14.0
Requires-Dist: ida-domain>=0.3.5
Dynamic: license-file
